<?xml version="1.0" encoding="utf-8"?>
<ChnPinyins>
<ChnPinyin>
<PinyinID>1</PinyinID>
<LevelID>17</LevelID>
<UnitID>1</UnitID>
<Phoneme>4|2</Phoneme>
<Chinese>共同</Chinese>
<English>common</English>
<Pinyin>ɡònɡ|tónɡ</Pinyin>
<PinyinNoPhoneme>ɡonɡ|tonɡ</PinyinNoPhoneme>
<Audio>ɡonɡtonɡ42.caf</Audio>
</ChnPinyin>
<ChnPinyin>
<PinyinID>2</PinyinID>
<LevelID>17</LevelID>
<UnitID>1</UnitID>
<Phoneme>1|0</Phoneme>
<Chinese>关系</Chinese>
<English>Relationship between</English>
<Pinyin>ɡuān|xi</Pinyin>
<PinyinNoPhoneme>ɡuɑn|xi</PinyinNoPhoneme>
<Audio>ɡuɑnxi10.caf</Audio>
</ChnPinyin>
<ChnPinyin>
<PinyinID>3</PinyinID>
<LevelID>17</LevelID>
<UnitID>1</UnitID>
<Phoneme>1|4</Phoneme>
<Chinese>观念</Chinese>
<English>concept</English>
<Pinyin>ɡuān|niàn</Pinyin>
<PinyinNoPhoneme>ɡuɑn|niɑn</PinyinNoPhoneme>
<Audio>ɡuɑnniɑn14.caf</Audio>
</ChnPinyin>
<ChnPinyin>
<PinyinID>4</PinyinID>
<LevelID>17</LevelID>
<UnitID>1</UnitID>
<Phoneme>2|4</Phoneme>
<Chinese>国际</Chinese>
<English>the international</English>
<Pinyin>ɡuó|jì</Pinyin>
<PinyinNoPhoneme>ɡuo|ji</PinyinNoPhoneme>
<Audio>ɡuoji24.caf</Audio>
</ChnPinyin>
<ChnPinyin>
<PinyinID>5</PinyinID>
<LevelID>17</LevelID>
<UnitID>1</UnitID>
<Phoneme>2|1</Phoneme>
<Chinese>国家</Chinese>
<English>countries</English>
<Pinyin>ɡuó|jiā</Pinyin>
<PinyinNoPhoneme>ɡuo|jiɑ</PinyinNoPhoneme>
<Audio>ɡuojiɑ21.caf</Audio>
</ChnPinyin>
<ChnPinyin>
<PinyinID>6</PinyinID>
<LevelID>17</LevelID>
<UnitID>1</UnitID>
<Phoneme>2|4</Phoneme>
<Chinese>国内</Chinese>
<English>domestic</English>
<Pinyin>ɡuó|nèi</Pinyin>
<PinyinNoPhoneme>ɡuo|nei</PinyinNoPhoneme>
<Audio>ɡuonei24.caf</Audio>
</ChnPinyin>
<ChnPinyin>
<PinyinID>7</PinyinID>
<LevelID>17</LevelID>
<UnitID>1</UnitID>
<Phoneme>4|2</Phoneme>
<Chinese>过程</Chinese>
<English>process</English>
<Pinyin>ɡuò|chénɡ</Pinyin>
<PinyinNoPhoneme>ɡuo|chenɡ</PinyinNoPhoneme>
<Audio>ɡuochenɡ42.caf</Audio>
</ChnPinyin>
<ChnPinyin>
<PinyinID>8</PinyinID>
<LevelID>17</LevelID>
<UnitID>1</UnitID>
<Phoneme>4|4</Phoneme>
<Chinese>过去</Chinese>
<English>in the past</English>
<Pinyin>ɡuò|qù</Pinyin>
<PinyinNoPhoneme>ɡuo|qu</PinyinNoPhoneme>
<Audio>ɡuoqu44.caf</Audio>
</ChnPinyin>
<ChnPinyin>
<PinyinID>9</PinyinID>
<LevelID>17</LevelID>
<UnitID>1</UnitID>
<Phoneme>2|4</Phoneme>
<Chinese>还是</Chinese>
<English>still</English>
<Pinyin>hái|shì</Pinyin>
<PinyinNoPhoneme>hɑi|shi</PinyinNoPhoneme>
<Audio>hɑishi24.caf</Audio>
</ChnPinyin>
<ChnPinyin>
<PinyinID>10</PinyinID>
<LevelID>17</LevelID>
<UnitID>1</UnitID>
<Phoneme>2|0</Phoneme>
<Chinese>孩子</Chinese>
<English>the child</English>
<Pinyin>hái|zi</Pinyin>
<PinyinNoPhoneme>hɑi|zi</PinyinNoPhoneme>
<Audio>hɑizi20.caf</Audio>
</ChnPinyin>
<ChnPinyin>
<PinyinID>11</PinyinID>
<LevelID>17</LevelID>
<UnitID>1</UnitID>
<Phoneme>2|2</Phoneme>
<Chinese>行为</Chinese>
<English>behavior</English>
<Pinyin>xínɡ|wéi</Pinyin>
<PinyinNoPhoneme>xinɡ|wei</PinyinNoPhoneme>
<Audio>xinɡwei22.caf</Audio>
</ChnPinyin>
<ChnPinyin>
<PinyinID>12</PinyinID>
<LevelID>17</LevelID>
<UnitID>1</UnitID>
<Phoneme>3|4</Phoneme>
<Chinese>好像</Chinese>
<English>as if</English>
<Pinyin>hǎo|xiànɡ</Pinyin>
<PinyinNoPhoneme>hɑo|xiɑnɡ</PinyinNoPhoneme>
<Audio>hɑoxiɑnɡ34.caf</Audio>
</ChnPinyin>
<ChnPinyin>
<PinyinID>13</PinyinID>
<LevelID>17</LevelID>
<UnitID>1</UnitID>
<Phoneme>3|1</Phoneme>
<Chinese>很多</Chinese>
<English>a lot of</English>
<Pinyin>hěn|duō</Pinyin>
<PinyinNoPhoneme>hen|duo</PinyinNoPhoneme>
<Audio>henduo31.caf</Audio>
</ChnPinyin>
<ChnPinyin>
<PinyinID>14</PinyinID>
<LevelID>17</LevelID>
<UnitID>1</UnitID>
<Phoneme>4|2</Phoneme>
<Chinese>后来</Chinese>
<English>later</English>
<Pinyin>hòu|lái</Pinyin>
<PinyinNoPhoneme>hou|lɑi</PinyinNoPhoneme>
<Audio>houlɑi42.caf</Audio>
</ChnPinyin>
<ChnPinyin>
<PinyinID>15</PinyinID>
<LevelID>17</LevelID>
<UnitID>1</UnitID>
<Phoneme>2|4</Phoneme>
<Chinese>环境</Chinese>
<English>the environment</English>
<Pinyin>huán|jìnɡ</Pinyin>
<PinyinNoPhoneme>huɑn|jinɡ</PinyinNoPhoneme>
<Audio>huɑnjinɡ24.caf</Audio>
</ChnPinyin>
</ChnPinyins>